dbbasic_rss/__init__.py
dbbasic_rss/feed.py
dbbasic_rss/generators.py
dbbasic_rss/templates.py
dbbasic_rss-1.0.0.dist-info/licenses/LICENSE
dbbasic_rss-1.0.0.dist-info/METADATA
dbbasic_rss-1.0.0.dist-info/WHEEL
dbbasic_rss-1.0.0.dist-info/top_level.txt
dbbasic_rss-1.0.0.dist-info/RECORD
