Metadata-Version: 2.4
Name: dbbasic-rss
Version: 1.0.0
Summary: Simple, composable RSS feed generation for Python. Framework-agnostic, works with TSV/CSV/JSON, follows Unix philosophy.
Author-email: Ask Robots <hello@askrobots.com>
License: MIT
Project-URL: Homepage, https://github.com/askrobots/dbbasic-rss
Project-URL: Documentation, https://github.com/askrobots/dbbasic-rss#readme
Project-URL: Repository, https://github.com/askrobots/dbbasic-rss
Project-URL: Issues, https://github.com/askrobots/dbbasic-rss/issues
Keywords: rss,feed,atom,xml,dbbasic,blog,podcast,syndication
Classifier: Development Status :: 4 - Beta
Classifier: Intended Audience :: Developers
Classifier: License :: OSI Approved :: MIT License
Classifier: Programming Language :: Python :: 3
Classifier: Programming Language :: Python :: 3.10
Classifier: Programming Language :: Python :: 3.11
Classifier: Programming Language :: Python :: 3.12
Classifier: Programming Language :: Python :: 3.13
Classifier: Topic :: Internet :: WWW/HTTP :: Dynamic Content :: News/Diary
Classifier: Topic :: Software Development :: Libraries :: Python Modules
Requires-Python: >=3.10
License-File: LICENSE
Provides-Extra: dev
Requires-Dist: pytest>=7.0.0; extra == "dev"
Requires-Dist: pytest-cov>=4.0.0; extra == "dev"
Provides-Extra: tsv
Requires-Dist: dbbasic-tsv>=1.0.0; extra == "tsv"
Provides-Extra: yaml
Requires-Dist: pyyaml>=6.0; extra == "yaml"
Dynamic: license-file
